matrx/__init__.py
matrx/__version__.py
matrx/defaults.py
matrx/grid_world.py
matrx/utils.py
matrx/world_builder.py
matrx/actions/__init__.py
matrx/actions/action.py
matrx/actions/door_actions.py
matrx/actions/move_actions.py
matrx/actions/object_actions.py
matrx/agents/__init__.py
matrx/agents/agent_brain.py
matrx/agents/agent_types/__init__.py
matrx/agents/agent_types/human_agent.py
matrx/agents/agent_types/patrolling_agent.py
matrx/agents/agent_utils/__init__.py
matrx/agents/agent_utils/navigator.py
matrx/agents/agent_utils/state_tracker.py
matrx/agents/agent_utils/task_manager.py
matrx/agents/capabilities/__init__.py
matrx/agents/capabilities/capability.py
matrx/api/__init__.py
matrx/api/api.py
matrx/cases/__init__.py
matrx/cases/simple_case.py
matrx/cases/test_case.py
matrx/cases/vis_test.py
matrx/goals/__init__.py
matrx/goals/goals.py
matrx/logger/__init__.py
matrx/logger/log_agent_actions.py
matrx/logger/log_idle_agents.py
matrx/logger/log_tick.py
matrx/logger/logger.py
matrx/messages/__init__.py
matrx/messages/message.py
matrx/messages/message_manager.py
matrx/objects/__init__.py
matrx/objects/agent_body.py
matrx/objects/env_object.py
matrx/objects/standard_objects.py
matrx_visualizer/__init__.py
matrx_visualizer/visualization_server.py
matrx_visualizer/mockup/css/GUI.css
matrx_visualizer/mockup/css/custom.css
matrx_visualizer/mockup/css/eraser.svg
matrx_visualizer/mockup/css/pencil-alt.svg
matrx_visualizer/mockup/html/agent_1.html
matrx_visualizer/mockup/html/start.html
matrx_visualizer/mockup/js/context_menu.js
matrx_visualizer/mockup/js/custom.js
matrx_visualizer/mockup/js/gen_grid.js
matrx_visualizer/mockup/js/init_grid.js
matrx_visualizer/mockup/js/init_grid2.js
matrx_visualizer/mockup/js/startscreen.js
matrx_visualizer/static/css/GUI.css
matrx_visualizer/static/css/eraser.svg
matrx_visualizer/static/css/pencil-alt.svg
matrx_visualizer/static/images/X.ico
matrx_visualizer/static/images/agent.gif
matrx_visualizer/static/images/city_bg_topdown.jpg
matrx-1.0.0.dist-info/LICENSE.txt
matrx-1.0.0.dist-info/METADATA
matrx-1.0.0.dist-info/WHEEL
matrx-1.0.0.dist-info/top_level.txt
matrx-1.0.0.dist-info/RECORD
