Metadata-Version: 2.1
Name: matrx
Version: 1.0.0
Summary: A Python package for the rapid development and evaluation of human-agent teaming concepts.
Home-page: https://matrx-software.com
Author: MATRX Team at TNO.nl
Author-email: info@matrx.com
License: MIT License
Project-URL: Documentation, http://docs.matrx-software.com/en/latest/
Project-URL: Source, https://github.com/matrx-software/matrx
Project-URL: Website, https://matrx-software.com
Platform: UNKNOWN
Classifier: Development Status :: 4 - Beta
Classifier: Programming Language :: Python :: 3
Classifier: Programming Language :: Python :: 3.6
Classifier: Programming Language :: Python :: 3.7
Classifier: Programming Language :: Python :: 3.8
Classifier: License :: OSI Approved :: MIT License
Classifier: Operating System :: OS Independent
Classifier: Topic :: Scientific/Engineering
Classifier: Intended Audience :: Science/Research
Classifier: Environment :: Web Environment
Requires-Dist: Flask (>=1.0.2)
Requires-Dist: Flask-SocketIO (>=3.3.2)
Requires-Dist: numpy (>=1.15.4)
Requires-Dist: requests (>=2.21.0)
Requires-Dist: colour (>=0.1.5)
Requires-Dist: gevent (>=1.4.0)
Requires-Dist: flask-cors (>=3.0.0)
